metaforecast/__init__.py
metaforecast/ensembles/__init__.py
metaforecast/ensembles/ade.py
metaforecast/ensembles/base.py
metaforecast/ensembles/expert_loss.py
metaforecast/ensembles/mlewa.py
metaforecast/ensembles/mlpol.py
metaforecast/ensembles/static.py
metaforecast/ensembles/windowing.py
metaforecast/longhorizon/__init__.py
metaforecast/longhorizon/ftn.py
metaforecast/synth/__init__.py
metaforecast/synth/callbacks.py
metaforecast/synth/generators/__init__.py
metaforecast/synth/generators/base.py
metaforecast/synth/generators/dba.py
metaforecast/synth/generators/jittering.py
metaforecast/synth/generators/kernelsynth.py
metaforecast/synth/generators/mbb.py
metaforecast/synth/generators/scaling.py
metaforecast/synth/generators/tsmixup.py
metaforecast/synth/generators/warping_mag.py
metaforecast/synth/generators/warping_time.py
metaforecast/utils/__init__.py
metaforecast/utils/barycenters.py
metaforecast/utils/data.py
metaforecast/utils/log.py
metaforecast/utils/normalization.py
metaforecast-0.2.2.dist-info/METADATA
metaforecast-0.2.2.dist-info/WHEEL
metaforecast-0.2.2.dist-info/RECORD
