Metadata-Version: 2.4
Name: metaforecast
Version: 0.2.2
Summary: Meta-learning and Data-centric Forecasting
Project-URL: Homepage, https://github.com/vcerqueira/metaforecast
Project-URL: Bug Tracker, https://github.com/vcerqueira/metaforecast/issues
Author-email: Vitor Cerqueira <cerqueira.vitormanuel@gmail.com>
Keywords: Data Science,Forecasting,Machine Learning,Time Series
Classifier: License :: OSI Approved :: MIT License
Classifier: Operating System :: OS Independent
Classifier: Programming Language :: Python :: 3
Requires-Python: >=3.8
Requires-Dist: arch==7.2.0
Requires-Dist: datasetsforecast==0.0.8
Requires-Dist: lightgbm==4.5.0
Requires-Dist: mlforecast==0.13.4
Requires-Dist: neuralforecast==1.7.5
Requires-Dist: pre-commit==4.0.1
Requires-Dist: pytorch-lightning==2.3.3
Requires-Dist: statsforecast==1.7.5
Requires-Dist: tslearn==0.6.3
